PyNUtools/__init__.py
PyNUtools-0.1.dist-info/LICENSE.txt
PyNUtools-0.1.dist-info/METADATA
PyNUtools-0.1.dist-info/WHEEL
PyNUtools-0.1.dist-info/top_level.txt
PyNUtools-0.1.dist-info/RECORD
