Metadata-Version: 2.1
Name: PyNUtools
Version: 0.1
License-File: LICENSE.txt
